{
  "General": "Informacion",
  "Path": "http://127.0.0.1:8887/",
  "Pages": {
    "Home": {
      "ID": "Home",
      "Name": "HomePage",
      "Layout": {
        "Name": "Site",
        "Path": "Disenos/sitio",
        "Sections": {
          "ips-section-0": {
            "ID": "ips-section-0",
            "Name": "ips-site-header",
            "Type": "header",
            "Order": -1,
            "Path": "Secciones/ips-header/ips-header",
            "Blocks": {
              "ips-block-0": {
                "ID": "ips-block-0",
                "Name": "Logo",
                "Type": "ips-nav-header",
                "Path": "Secciones/ips-header-ips-header",
                "Content": {
                  "logo": "",
                  "link": ""
                },
                "Config": {
                  "logo": {
                    "ID": "logo",
                    "Type": "text",
                    "Label": "Logo",
                    "DefaultContent": "Logo"
                  },
                  "link": {
                    "ID": "link",
                    "Type": "text",
                    "Label": "Enlace",
                    "DefaultContent": "#"
                  }
                }
              },
              "ips-block-1": {
                "ID": "ips-block-1",
                "Name": "Lista",
                "Type": "ips-nav-list",
                "Path": "Secciones/ips-header-ips-header",
                "Content": {
                  "link": {
                    "link-0": {
                      "link-name": "Home",
                      "link-value": "https://www.google.com/"
                    },
                    "link-1": {
                      "link-name": "About",
                      "link-value": "#"
                    },
                    "link-2": {
                      "link-name": "Service",
                      "link-value": "#"
                    },
                    "link-3": {
                      "link-name": "Gallery",
                      "link-value": "#"
                    },
                    "link-4": {
                      "link-name": "Contact Us",
                      "link-value": "#"
                    }
                  },
                  "other": {
                    "other-0": {
                      "search-name": "Search",
                      "search-value": "#"
                    }
                  }
                },
                "Config": {
                  "link": {
                    "ID": "link",
                    "Type": "item-selector",
                    "Label": "Enlaces",
                    "DefaultContent": {
                      "link-0": {
                        "link-name": "link1",
                        "link-value": "#"
                      },
                      "link-1": {
                        "link-name": "link2",
                        "link-value": "#"
                      },
                      "link-2": {
                        "link-name": "link3",
                        "link-value": "#"
                      }
                    }
                  },
                  "other": {
                    "ID": "other",
                    "Type": "item-selector",
                    "Label": "Otros Enlaces",
                    "DefaultContent": {
                      "other-0": {
                        "search-name": "Search",
                        "search-value": "#"
                      }
                    }
                  },
                  "link-items-config": {
                    "link-name": {
                      "ID": "link-name",
                      "Type": "text",
                      "Label": "Etiqueta",
                      "DefaultContent": "Link"
                    },
                    "link-value": {
                      "ID": "link-value",
                      "Type": "text",
                      "Label": "Enlace",
                      "DefaultContent": "#"
                    }
                  },
                  "other-items-config": {
                    "search-name": {
                      "ID": "search-name",
                      "Type": "text",
                      "Label": "Etiqueta",
                      "DefaultContent": "Link"
                    },
                    "search-value": {
                      "ID": "search-value",
                      "Type": "text",
                      "Label": "Enlace",
                      "DefaultContent": "#"
                    }
                  }
                }
              }
            }
          },
          "ips-section-1": {
            "ID": "ips-section-1",
            "Name": "ips-site-footer",
            "Type": "footer",
            "Order": 1,
            "Path": "Secciones/ips-footer/ips-footer",
            "Blocks": {
              "ips-block-0": {
                "ID": "ips-block-0",
                "Name": "Menu",
                "Type": "ips-footer-nav-list",
                "Path": "Bloques/ips-footer/ips-footer",
                "Content": {
                  "title": "Nosotros",
                  "link": {
                    "link-0": {
                      "link-name": "Sobre Nosotros",
                      "link-value": "https://www.google.com/"
                    },
                    "link-1": {
                      "link-name": "Nuestra Historia",
                      "link-value": "#"
                    },
                    "link-2": {
                      "link-name": "Sobre Nosotros",
                      "link-value": "#"
                    }
                  }
                },
                "Config": {
                  "title": {
                    "ID": "title",
                    "Type": "text",
                    "Label": "Titulo",
                    "DefaultContent": "Menu"
                  },
                  "link": {
                    "ID": "link",
                    "Type": "item-selector",
                    "Label": "Enlaces",
                    "DefaultContent": {
                      "link-0": {
                        "link-name": "link1",
                        "link-value": "#"
                      },
                      "link-1": {
                        "link-name": "link2",
                        "link-value": "#"
                      },
                      "link-2": {
                        "link-name": "link3",
                        "link-value": "#"
                      }
                    }
                  },
                  "link-items-config": {
                    "link-name": {
                      "ID": "link-name",
                      "Type": "text",
                      "Label": "Etiqueta",
                      "DefaultContent": "Link"
                    },
                    "link-value": {
                      "ID": "link-value",
                      "Type": "text",
                      "Label": "Enlace",
                      "DefaultContent": "#"
                    }
                  }
                }
              },
              "ips-block-1": {
                "ID": "ips-block-1",
                "Name": "Social",
                "Type": "ips-footer-social-list",
                "Path": "Bloques/ips-footer/ips-footer",
                "Content": {
                  "title": "",
                  "link": {
                    "link-0": {
                      "link-name": "facebook",
                      "link-value": "#"
                    },
                    "link-1": {
                      "link-name": "instagram",
                      "link-value": "#"
                    },
                    "link-2": {
                      "link-name": "twitter",
                      "link-value": "#"
                    }
                  }
                },
                "Config": {
                  "title": {
                    "ID": "title",
                    "Type": "text",
                    "Label": "Titulo",
                    "DefaultContent": "Social"
                  },
                  "link": {
                    "ID": "link",
                    "Type": "item-selector",
                    "Label": "Enlaces",
                    "DefaultContent": {
                      "link-0": {
                        "link-name": "facebook",
                        "link-value": "#"
                      },
                      "link-1": {
                        "link-name": "instagram",
                        "link-value": "#"
                      },
                      "link-2": {
                        "link-name": "twitter",
                        "link-value": "#"
                      }
                    }
                  },
                  "link-items-config": {
                    "link-name": {
                      "ID": "link-name",
                      "Type": "text",
                      "Label": "Etiqueta",
                      "DefaultContent": "Facebook"
                    },
                    "link-value": {
                      "ID": "link-value",
                      "Type": "text",
                      "Label": "Enlace",
                      "DefaultContent": "#"
                    }
                  }
                }
              },
              "ips-block-2": {
                "ID": "ips-block-2",
                "Name": "Paragraph",
                "Type": "ips-footer-text",
                "Path": "Bloques/ips-footer/ips-footer",
                "Content": {
                  "title": "Mi empresa",
                  "text": "Cualquier cosa que quieras saber sobre nosotros solo escribenos."
                },
                "Config": {
                  "title": {
                    "ID": "title",
                    "Type": "text",
                    "Label": "Titulo",
                    "DefaultContent": "Titulo"
                  },
                  "text": {
                    "ID": "text",
                    "Type": "text",
                    "Label": "Texto",
                    "DefaultContent": "Cualquier texto para que este apartado no se quede vacio"
                  }
                }
              },
              "ips-block-3": {
                "ID": "ips-block-3",
                "Name": "Newsletter",
                "Type": "ips-footer-newsletter",
                "Path": "Bloques/ips-footer/ips-footer",
                "Content": {
                  "title": "",
                  "text": "",
                  "btn-label": ""
                },
                "Config": {
                  "title": {
                    "ID": "title",
                    "Type": "text",
                    "Label": "Titulo",
                    "DefaultContent": "Noticias"
                  },
                  "text": {
                    "ID": "text",
                    "Type": "text",
                    "Label": "Texto",
                    "DefaultContent": "Suscribete para saber todas las noticias al momento!"
                  },
                  "btn-label": {
                    "ID": "btn-label",
                    "Type": "text",
                    "Label": "Etiqueta",
                    "DefaultContent": "Suscribete"
                  }
                }
              }
            }
          }
        } 
      },
      "Template":{
        "Name": "Portada",
        "Path": "Plantilla/portada",
        "Blocks": {
          "ips-block-0": {
            "ID": "ips-block-0",
            "Name": "Slideshow",
            "Type": "ips-slideshow",
            "Path": "Bloques/ips-slideshow/ips-slideshow",
            "Content": {
              "slide": {
                "slide-0": {
                  "image": "http://127.0.0.1:8887/Recursos/Imagenes/banner2.png",
                  "title": "Cafe",
                  "text": "",
                  "btn-label": "Ver mas",
                  "btn-link": "#"
                },
                "slide-1": {
                  "image": "http://127.0.0.1:8887/Recursos/Imagenes/banner1.jpg",
                  "title": "Cafeina",
                  "text": "",
                  "btn-label": "Ver mas",
                  "btn-link": "#"
                }
              },
              "auto-scroll": "true"
            },
            "Config": {
              "slide": {
                "ID": "slide",
                "Type": "item-selector",
                "Label": "Slides",
                "DefaultContent": {
                  "slide-0": {
                    "image": "http://127.0.0.1:8887/Recursos/Imagenes/banner1.jpg",
                    "title": "Categoria 1",
                    "text": "It is a long established fact that a reader will be distracted by the readable content of a page when looking at its layout. The point of using Lorem Ipsum is that it has a more-or-less normal distribution of letters, as opposed to using 'Content here, content here', making it look like readable English. Many desktop publishing packages and",
                    "btn-label": "Ver",
                    "btn-link": "#"
                  },
                  "slide-1": {
                    "image": "http://127.0.0.1:8887/Recursos/Imagenes/banner2.png",
                    "title": "Categoria 1",
                    "text": "It is a long established fact that a reader will be distracted by the readable content of a page when looking at its layout. The point of using Lorem Ipsum is that it has a more-or-less normal distribution of letters, as opposed to using 'Content here, content here', making it look like readable English. Many desktop publishing packages and",
                    "btn-label": "Ver",
                    "btn-link": "#"
                  }
                }
              },
              "auto-scroll": {
                "ID": "auto-scroll",
                "Type": "checkBox",
                "Label": "Slide automatico",
                "DefaultContent": "true"
              },
              "slide-items-config": {
                "image": {
                  "ID": "image",
                  "Type": "file",
                  "Label": "Imagen",
                  "DefaultContent": "http://127.0.0.1:8887/Recursos/Imagenes/banner2.png"
                },
                "title": {
                  "ID": "title",
                  "Type": "text",
                  "Label": "Titulo",
                  "DefaultContent": "Cafe"
                },
                "text": {
                  "ID": "text",
                  "Type": "text",
                  "Label": "Texto",
                  "DefaultContent": ""
                },
                "btn-label": {
                  "ID": "btn-label",
                  "Type": "text",
                  "Label": "Etiqueta del Boton",
                  "DefaultContent": ""
                },
                "btn-link": {
                  "ID": "btn-link",
                  "Type": "text",
                  "Label": "Link",
                  "DefaultContent": ""                  
                }
              }
            }
          },
          "ips-block-1": {
            "ID": "ips-block-1",
            "Name": "Image with Text",
            "Type": "ips-image-text",
            "Path": "Bloques/ips-image-text/ips-image-text",
            "Content": {
              "image": "",
              "title": "Prueba",
              "text": "Esto es un texto de ejemplo para llenar algo y realmente no se porque se lleno tan corto"
            },
            "Config": {
              "image": {
                "ID": "image",
                "Type": "file",
                "Label": "Imagen",
                "DefaultContent": "http://127.0.0.1:8887/Recursos/Imagenes/img2.jpg"
              },
              "title": {
                "ID": "title",
                "Type": "text",
                "Label": "Titulo",
                "DefaultContent": "Texto con Imagen"
              },
              "text": {
                "ID": "text",
                "Type": "richtext",
                "Label": "Texto",
                "DefaultContent": "It is a long established fact that a reader will be distracted by the readable content of a page when looking at its layout. The point of using Lorem Ipsum is that it has a more-or-less normal distribution of letters, as opposed to using 'Content here, content here', making it look like readable English. Many desktop publishing packages and"
              }
            }
          },
          "ips-block-2": {
            "ID": "ips-block-2",
            "Name": "Simple Text",
            "Type": "ips-simple-text",
            "Path": "Bloques/ips-simple-text/ips-simple-text",
            "Content": {
              "title": "",
              "text": ""
            },
            "Config": {
              "title": {
                "ID": "title",
                "Type": "text",
                "Label": "Titulo",
                "DefaultContent": "Information"
              },
              "text": {
                "ID": "text",
                "Type": "textarea",
                "Label": "Texto",
                "DefaultContent": "Lorem ipsum dolor sit amet consectetur adipisicing elit. Reprehenderit dolorem fugit nihil sed, ipsum reiciendis blanditiis, nisi nobis magni, nulla fugiat dolore? Totam, odit? Eius delectus dolorem atque cupiditate pariatur velit iure ipsum natus at minus inventore autem accusamus quod, repellat asperiores architecto iusto sequi similique doloremque expedita. Quod libero ratione temporibus unde provident delectus voluptates amet, porro accusamus placeat modi enim totam iste laborum possimus ducimus quidem nobis sapiente ipsum corporis accusantium? Qui sint iste cumque eum molestias eius fugiat at eos voluptatibus inventore! Facere temporibus ipsa ipsum neque repudiandae recusandae asperiores natus illo accusantium, est iure quaerat quibusdam!"
              }
            }
          },
          "ips-block-3": {
            "ID": "ips-block-3",
            "Name": "Product List",
            "Type": "ips-product-list",
            "Path": "Bloques/ips-product-list/ips-product-list",
            "Content": {
              "product": {},
              "title": ""
            },
            "Config": {
              "product": {
                "ID": "product",
                "Type": "item-selector",
                "Label": "Productos",
                "DefaultContent": {
                  "product-0": {
                    "image": "http://127.0.0.1:8887/Recursos/Imagenes/img1.jpg",
                    "name": "Producto",
                    "details": "Detalle Producto",
                    "price": 100
                  },
                  "product-1": {
                    "image": "http://127.0.0.1:8887/Recursos/Imagenes/img2.jpg",
                    "name": "Producto",
                    "details": "Detalle Producto",
                    "price": 200
                  },
                  "product-2": {
                    "image": "http://127.0.0.1:8887/Recursos/Imagenes/img3.jpg",
                    "name": "Producto",
                    "details": "Detalle Producto",
                    "price": 200
                  },
                  "product-3": {
                    "image": "http://127.0.0.1:8887/Recursos/Imagenes/img4.jpg",
                    "name": "Producto",
                    "details": "Detalle Producto",
                    "price": 200
                  }
                }
              },
              "title": {
                "ID": "title",
                "Type": "text",
                "Label": "Titulo",
                "DefaultContent": "Product List"
              },
              "product-items-config": {
                "image": {
                  "ID": "image",
                  "Type": "file",
                  "Label": "Imagen",
                  "defaultcontent": "http://127.0.0.1:8887/Recursos/Imagenes/img1.jpg"
                },
                "name": {
                  "ID": "name",
                  "Type": "text",
                  "Label": "Nombre",
                  "DefaultContent": "Producto"
                },
                "details": {
                  "ID": "details",
                  "Type": "text",
                  "Label": "Detalles",
                  "DefaultContent": "Detalles Producto"
                },
                "price": {
                  "ID": "price",
                  "Type": "number",
                  "Label": "Precio",
                  "DefaultContent": 100
                }
              }
            }
          },
          "ips-block-4": {
            "ID": "ips-block-4",
            "Name": "Image Group",
            "Type": "ips-image-group",
            "Path": "Bloques/ips-image-group/ips-image-group",
            "Content": {
              "image": {},
              "title": ""
            },
            "Config": {
              "image": {
                "ID": "image",
                "Type": "item-selector",
                "Label": "Imagenes",
                "DefaultContent": {
                  "image-0": {
                    "img": "http://127.0.0.1:8887/Recursos/Imagenes/img1.jpg",
                    "title": ""
                  },
                  "image-1": {
                    "img": "http://127.0.0.1:8887/Recursos/Imagenes/img2.jpg",
                    "title": ""
                  }
                }
              },
              "title": {
                "ID": "title",
                "Type": "text",
                "Label": "Titulo",
                "DefaultContent": ""
              },
              "image-items-config": {
                "img": {
                  "ID": "img",
                  "Type": "file",
                  "Label": "Imagen",
                  "DefaultContent": "http://127.0.0.1:8887/Recursos/Imagenes/img1.jpg"
                },
                "title": {
                  "ID": "title",
                  "Type": "text",
                  "Label": "Titulo",
                  "DefaultContent": ""
                }
              }
            }
          }
        }
      }
    }
  }
}